MANIFEST.in
README.rst
setup.py
ircmessage/__init__.py
ircmessage/colors.py
ircmessage.egg-info/PKG-INFO
ircmessage.egg-info/SOURCES.txt
ircmessage.egg-info/dependency_links.txt
ircmessage.egg-info/requires.txt
ircmessage.egg-info/top_level.txt