Metadata-Version: 1.1
Name: ircmessage
Version: 0.1.0
Summary: A simple Python module for applying and stripping formatting from IRC messages.
Home-page: https://github.com/FujiMakoto/IRC-Message-Formatter
Author: Makoto Fujimoto
Author-email: makoto@makoto.io
License: MIT
Keywords: irc
Platform: UNKNOWN
Classifier: Development Status :: 3 - Alpha
Classifier: License :: OSI Approved :: MIT License
Classifier: Intended Audience :: Developers
Classifier: Topic :: Communications :: Chat :: Internet Relay Chat
Classifier: Topic :: Text Processing
